{
  "organization":"asm",
  "name":"asm-tree",
  "version":"3.3",
  "modules":[{
    "unique-id":"asm:asm-tree:3.3-0205ba6",
    "artifacts":[{
      "hash":"33c13070f194e1f0385877ec9306a24e983b00e3",
      "artifact-type":"jar",
      "configurations":["master"],
      "locations":["http://repo1.maven.org/maven2/asm/asm-tree/3.3/asm-tree-3.3.jar"]
    }],
    "dependencies":[{
      "organization":"asm",
      "name":"asm",
      "version":"3.3",
      "configuration":"compile->compile(*),master(*);runtime->runtime(*)",
      "force":true
    }],
    "overrides":[{
      "organization":"asm",
      "name":"asm-tree",
      "override-version":"3.3"
    },{
      "organization":"asm",
      "name":"asm-analysis",
      "override-version":"3.3"
    },{
      "organization":"asm",
      "name":"asm",
      "override-version":"3.3",
      "unique-id":"asm:asm:3.3-6e65da4"
    },{
      "organization":"asm",
      "name":"asm-commons",
      "override-version":"3.3",
      "unique-id":"asm:asm-commons:3.3-1c38b12"
    },{
      "organization":"asm",
      "name":"asm-xml",
      "override-version":"3.3"
    },{
      "organization":"asm",
      "name":"asm-util",
      "override-version":"3.3",
      "unique-id":"asm:asm-util:3.3-3269dd8"
    }],
    "configurations":[{
      "name":"system",
      "description":"this scope is similar to provided except that you have to provide the JAR which contains it explicitly. The artifact is always available and is not looked up in a repository.",
      "visibility":"public"
    },{
      "name":"master",
      "description":"contains only the artifact published by this module itself, with no transitive dependencies",
      "visibility":"public"
    },{
      "name":"compile",
      "description":"this is the default scope, used if none is specified. Compile dependencies are available in all classpaths.",
      "visibility":"public"
    },{
      "name":"provided",
      "description":"this is much like compile, but indicates you expect the JDK or a container to provide it. It is only available on the compilation classpath, and is not transitive.",
      "visibility":"public"
    },{
      "name":"runtime",
      "description":"this scope indicates that the dependency is not required for compilation, but is for execution. It is in the runtime and test classpaths, but not the compile classpath.",
      "visibility":"public",
      "extends":["compile"]
    },{
      "name":"test",
      "description":"this scope indicates that the dependency is not required for normal use of the application, and is only available for the test compilation and execution phases.",
      "visibility":"private",
      "extends":["runtime"]
    },{
      "name":"default",
      "description":"runtime dependencies and master artifact can be used with this conf",
      "visibility":"public",
      "extends":["runtime","master"]
    },{
      "name":"optional",
      "description":"contains all optional dependencies",
      "visibility":"public"
    },{
      "name":"javadoc",
      "description":"this configuration contains the javadoc artifact of this module, if any.",
      "visibility":"public"
    },{
      "name":"sources",
      "description":"this configuration contains the source artifact of this module, if any.",
      "visibility":"public"
    }]
  }]
}